## 0x05. Python - Exceptions
  <h4 class="task">
    0. Safe list printing
      <span class="alert alert-warning mandatory-optional">
        mandatory
      </span>
  </h4>


  <!-- Progress vs Score -->

<!-- Task Body -->
  <p>Write a function that prints <code>x</code> elements of a list.</p>

<ul>
<li>Prototype: <code>def safe_print_list(my_list=[], x=0):</code></li>
<li><code>my_list</code> can contain any type (integer, string, etc.)</li>
<li>All elements must be printed on the same line followed by a new line.</li>
<li><code>x</code> represents the number of elements to print</li>
<li><code>x</code> can be bigger than the length of <code>my_list</code></li>
<li>Returns the real number of elements printed</li>
<li>You have to use <code>try: / except:</code> </li>
<li>You are not allowed to import any module</li>
<li>You are not allowed to use <code>len()</code></li>
</ul>
  <h4 class="task">
    1. Safe printing of an integers list
      <span class="alert alert-warning mandatory-optional">
        mandatory
      </span>
  </h4>


  <!-- Progress vs Score -->

<!-- Task Body -->
  <p>Write a function that prints an integer with <code>&quot;{:d}&quot;.format()</code>.</p>

<ul>
<li>Prototype: <code>def safe_print_integer(value):</code></li>
<li><code>value</code> can be any type (integer, string, etc.)</li>
<li>The integer should be printed followed by a new line</li>
<li>Returns <code>True</code> if <code>value</code> has been correctly printed (it means the <code>value</code> is an integer)</li>
<li>Otherwise, returns <code>False</code></li>
<li>You have to use <code>try: / except:</code> </li>
<li>You have to use <code>&quot;{:d}&quot;.format()</code> to print as integer</li>
<li>You are not allowed to import any module</li>
<li>You are not allowed to use <code>type()</code></li>
</ul>
  <h4 class="task">
    2. Print and count integers
      <span class="alert alert-warning mandatory-optional">
        mandatory
      </span>
  </h4>


  <!-- Progress vs Score -->

<!-- Task Body -->
  <p>Write a function that prints the first <code>x</code> elements of a list and only integers.</p>

<ul>
<li>Prototype: <code>def safe_print_list_integers(my_list=[], x=0):</code></li>
<li><code>my_list</code> can contain any type (integer, string, etc.)</li>
<li>All integers have to be print in the same line followed by a new line.</li>
<li><code>x</code> represents the number of elements to access in <code>my_list</code></li>
<li><code>x</code> can be bigger than the length of <code>my_list</code></li>
<li>Returns the real number of integers printed</li>
<li>You have to use <code>try: / except:</code> </li>
<li>You have to use <code>&quot;{:d}&quot;.format()</code> to print an integer</li>
<li>You are not allowed to import any module</li>
<li>You are not allowed to use <code>len()</code></li>
</ul>
  <h4 class="task">
    3. Integers division with debug
      <span class="alert alert-warning mandatory-optional">
        mandatory
      </span>
  </h4>


  <!-- Progress vs Score -->

<!-- Task Body -->
  <p>Write a function that divides 2 integers and prints the result.</p>

<ul>
<li>Prototype: <code>def safe_print_division(a, b):</code></li>
<li>You can assume that <code>a</code> and <code>b</code> are integers</li>
<li>The result of the division should print in the <code>finally:</code> section preceded by <code>Inside result:</code></li>
<li>Returns the value of the division, otherwise: <code>None</code></li>
<li>You have to use <code>try: / except: / finally:</code> </li>
<li>You have to use <code>&quot;{}&quot;.format()</code> to print the result</li>
<li>You are not allowed to import any module</li>
</ul>
  <h4 class="task">
    4. Divide a list
      <span class="alert alert-warning mandatory-optional">
        mandatory
      </span>
  </h4>


  <!-- Progress vs Score -->

<!-- Task Body -->
  <p>Write a function that divides element by element 2 lists.</p>

<ul>
<li>Prototype: <code>def list_division(my_list_1, my_list_2, list_length):</code></li>
<li><code>my_list_1</code> and <code>my_list_2</code> can contain any type (integer, string, etc.)</li>
<li><code>list_length</code> can be bigger than the length of both lists</li>
<li>Returns a new list (length = <code>list_length</code>) with all divisions</li>
<li>If 2 elements can&#39;t be divided, the division result should be equal to <code>0</code></li>
<li>If an element is not an integer or float:

<ul>
<li>print: <code>wrong type</code></li>
</ul></li>
<li>If the division can&#39;t be done (<code>/0</code>):

<ul>
<li>print: <code>division by 0</code></li>
</ul></li>
<li>If <code>my_list_1</code> or <code>my_list_2</code> is too short

<ul>
<li>print: <code>out of range</code></li>
</ul></li>
<li>You have to use <code>try: / except: / finally:</code> </li>
<li>You are not allowed to import any module</li>
</ul>
  <h4 class="task">
    5. Raise exception
      <span class="alert alert-warning mandatory-optional">
        mandatory
      </span>
  </h4>


  <!-- Progress vs Score -->

<!-- Task Body -->
  <p>Write a function that raises a type exception.</p>

<ul>
<li>Prototype: <code>def raise_exception():</code></li>
<li>You are not allowed to import any module</li>
</ul>
  <h4 class="task">
    6. Raise a message
      <span class="alert alert-warning mandatory-optional">
        mandatory
      </span>
  </h4>


  <!-- Progress vs Score -->

<!-- Task Body -->
  <p>Write a function that raises a name exception with a message.</p>

<ul>
<li>Prototype: <code>def raise_exception_msg(message=&quot;&quot;):</code></li>
<li>You are not allowed to import any module</li>
</ul>
  <h4 class="task">
    7. Safe integer print with error message
      <span class="alert alert-info mandatory-optional">
        #advanced
      </span>
  </h4>


  <!-- Progress vs Score -->

<!-- Task Body -->
  <p>Write a function that prints an integer.</p>

<ul>
<li>Prototype: <code>def safe_print_integer_err(value):</code></li>
<li><code>value</code> can be any type (integer, string, etc.)</li>
<li>The integer should be printed followed by a new line</li>
<li>Returns <code>True</code> if <code>value</code> has been correctly printed (it means the <code>value</code> is an integer)</li>
<li>Otherwise, returns <code>False</code> and prints in <code>stderr</code> the error precede by <code>Exception:</code></li>
<li>You have to use <code>try: / except:</code> </li>
<li>You have to use <code>&quot;{:d}&quot;.format()</code> to print as integer</li>
<li>You are not allowed to use <code>type()</code></li>
</ul>
  <h4 class="task">
    8. Safe function
      <span class="alert alert-info mandatory-optional">
        #advanced
      </span>
  </h4>


  <!-- Progress vs Score -->

<!-- Task Body -->
  <p>Write a function that executes a function safely.  </p>

<ul>
<li>Prototype: <code>def safe_function(fct, *args):</code></li>
<li>You can assume <code>fct</code> will be always a pointer to a function</li>
<li>Returns the result of the function,</li>
<li>Otherwise, returns <code>None</code> if something happens during the function and prints in <code>stderr</code> the error precede by <code>Exception:</code></li>
<li>You have to use <code>try: / except:</code> </li>
</ul>
  <h4 class="task">
    9. ByteCode -&gt; Python #4
      <span class="alert alert-info mandatory-optional">
        #advanced
      </span>
  </h4>


  <!-- Progress vs Score -->

<!-- Task Body -->
  <p>Write the Python function <code>def magic_calculation(a, b):</code> that does exactly the same as the following Python bytecode:</p>

<pre><code>  3           0 LOAD_CONST               1 (0)
              3 STORE_FAST               2 (result)

  4           6 SETUP_LOOP              94 (to 103)
              9 LOAD_GLOBAL              0 (range)
             12 LOAD_CONST               2 (1)
             15 LOAD_CONST               3 (3)
             18 CALL_FUNCTION            2 (2 positional, 0 keyword pair)
             21 GET_ITER
        &gt;&gt;   22 FOR_ITER                77 (to 102)
             25 STORE_FAST               3 (i)

  5          28 SETUP_EXCEPT            49 (to 80)

  6          31 LOAD_FAST                3 (i)
             34 LOAD_FAST                0 (a)
             37 COMPARE_OP               4 (&gt;)
             40 POP_JUMP_IF_FALSE       58

  7          43 LOAD_GLOBAL              1 (Exception)
             46 LOAD_CONST               4 (&#39;Too far&#39;)
             49 CALL_FUNCTION            1 (1 positional, 0 keyword pair)
             52 RAISE_VARARGS            1
             55 JUMP_FORWARD            18 (to 76)

  9     &gt;&gt;   58 LOAD_FAST                2 (result)
             61 LOAD_FAST                0 (a)
             64 LOAD_FAST                1 (b)
             67 BINARY_POWER
             68 LOAD_FAST                3 (i)
             71 BINARY_TRUE_DIVIDE
             72 INPLACE_ADD
             73 STORE_FAST               2 (result)
        &gt;&gt;   76 POP_BLOCK
             77 JUMP_ABSOLUTE           22

 10     &gt;&gt;   80 POP_TOP
             81 POP_TOP
             82 POP_TOP

 11          83 LOAD_FAST                1 (b)
             86 LOAD_FAST                0 (a)
             89 BINARY_ADD
             90 STORE_FAST               2 (result)

 12          93 BREAK_LOOP
             94 POP_EXCEPT
             95 JUMP_ABSOLUTE           22
             98 END_FINALLY
             99 JUMP_ABSOLUTE           22
        &gt;&gt;  102 POP_BLOCK

 13     &gt;&gt;  103 LOAD_FAST                2 (result)
            106 RETURN_VALUE
</code></pre>

<ul>
<li>Tip: <a href="https://docs.python.org/3.4/library/dis.html">Python bytecode</a></li>
</ul>
